djarg/__init__.py
djarg/forms.py
djarg/tests/__init__.py
djarg/tests/templates/tests/grant_staff_access.html
djarg/tests/templates/tests/grant_staff_access_wizard.html
djarg/tests/test_integration.py
djarg/tests/test_utils.py
djarg/tests/urls.py
djarg/tests/views.py
djarg/utils.py
djarg/views.py
django_args-1.4.0.dist-info/LICENSE
django_args-1.4.0.dist-info/WHEEL
django_args-1.4.0.dist-info/METADATA
django_args-1.4.0.dist-info/RECORD
