Metadata-Version: 2.1
Name: django-args
Version: 1.4.0
Summary: Django wrappers for python-args functions.
Home-page: https://github.com/jyveapp/django-args
License: BSD-3-Clause
Author: Wes Kendall
Requires-Python: >=3.6,<4
Classifier: Framework :: Django
Classifier: Intended Audience :: Developers
Classifier: License :: OSI Approved :: BSD License
Classifier: Operating System :: OS Independent
Classifier: Programming Language :: Python
Classifier: Programming Language :: Python :: 3
Classifier: Programming Language :: Python :: 3 :: Only
Classifier: Programming Language :: Python :: 3.6
Classifier: Programming Language :: Python :: 3.7
Classifier: Programming Language :: Python :: 3.8
Requires-Dist: django (>=2)
Requires-Dist: django-formtools (>=2.2,<3.0)
Requires-Dist: python-args (>=1.0.2,<2.0.0)
Project-URL: Documentation, https://django-args.readthedocs.io
Project-URL: Repository, https://github.com/jyveapp/django-args
